deep_sorted/__init__.py
deep_sorted/_deep_sorted.py
deep_sorted-0.0.3.dist-info/LICENSE
deep_sorted-0.0.3.dist-info/METADATA
deep_sorted-0.0.3.dist-info/WHEEL
deep_sorted-0.0.3.dist-info/RECORD
