Metadata-Version: 2.1
Name: deep-sorted
Version: 0.0.3
Summary: Sorting of nested dicts and lists
Home-page: https://github.com/danhje/deep-sorted
License: MIT
Keywords: sort,sorted,nested,recursive,deep,dict,list
Author: Daniel Hjertholm
Author-email: daniel.hjertholm@icloud.com
Requires-Python: >=3.8.1,<4.0
Classifier: Development Status :: 4 - Beta
Classifier: Intended Audience :: Developers
Classifier: License :: OSI Approved :: MIT License
Classifier: Natural Language :: English
Classifier: Operating System :: OS Independent
Classifier: Programming Language :: Python :: 3
Classifier: Programming Language :: Python :: 3.9
Classifier: Programming Language :: Python :: 3.10
Classifier: Programming Language :: Python :: 3.11
Classifier: Topic :: Software Development :: Libraries
Classifier: Topic :: Software Development :: Libraries :: Python Modules
Project-URL: Repository, https://github.com/danhje/deep-sorted
